imxdparser/__init__.py
imxdparser/imxdparser.py
imxdparser-1.0.12.dist-info/LICENSE
imxdparser-1.0.12.dist-info/METADATA
imxdparser-1.0.12.dist-info/WHEEL
imxdparser-1.0.12.dist-info/top_level.txt
imxdparser-1.0.12.dist-info/zip-safe
imxdparser-1.0.12.dist-info/RECORD
