Metadata-Version: 2.1
Name: imxdparser
Version: 1.0.12
Summary: Intermixed argparser, aka imxdparser, and based only on argparse, is an argument parser that allows the unordered, and intermixed, optional and positional arguments.
Author-email: Julien Lecomte <julien@lecomte.at>
License: MIT
Project-URL: Homepage, https://gitlab.com/cappysan/imxdparser
Project-URL: Documentation, https://imxdparser.docs.cappysan.dev
Project-URL: Source code, https://gitlab.com/cappysan/imxdparser
Project-URL: Bug tracker, https://gitlab.com/cappysan/imxdparser/-/issues
Classifier: License :: OSI Approved :: MIT License
Classifier: Intended Audience :: Developers
Classifier: Development Status :: 5 - Production/Stable
Classifier: Programming Language :: Python :: 3 :: Only
Classifier: Programming Language :: Python :: 3.7
Classifier: Programming Language :: Python :: 3.8
Classifier: Programming Language :: Python :: 3.9
Classifier: Programming Language :: Python :: 3.10
Classifier: Programming Language :: Python :: 3.11
Classifier: Programming Language :: Python :: 3.12
Requires-Python: >=3.7
License-File: LICENSE
Provides-Extra: dev
